{
  "name": "spark-in",
  "title": "spark-in",
  "summary": "spark-in",
  "dxapi": "1.0.0",
  "version": "0.0.1",
  "inputSpec": [],
  "outputSpec": [],
  "runSpec": {
    "timeoutPolicy": {
      "*": {
        "hours": 4
      }
    },
    "interpreter": "python3",
    "file": "src/spark-in.py",
    "distribution": "Ubuntu",
    "release": "24.04",
    "version": "0"
  },
  "access": {
    "network": [
      "*"
    ],
    "project": "CONTRIBUTE"
  },
  "regionalOptions": {
    "aws:eu-west-2": {
      "systemRequirements": {
        "*": {
          "instanceType": "mem1_ssd1_v2_x4",
          "clusterSpec": {
            "type": "dxspark",
            "version": "3.5.2",
            "initialInstanceCount": 2,
            "ports": "9500, 9700-9750"
          }
        }
      }
    }
  }
}

