
{
	"name": "aikb",
	// Or use a Dockerfile or Docker Compose file. More info: https://containers.dev/guide/dockerfile
	"dockerComposeFile": "docker-compose.yml",
    "service": "app",
    "workspaceFolder": "/workspace/",
	"customizations": {
		"vscode": {
			"extensions": [
				"boundary.baml-extension",
				"ms-python.vscode-pylance",
				"rooveterinaryinc.roo-cline",
				"naveenvignesh5nv.html-live-server",
				"shellomo.enhanced-toml",
				"zxh404.vscode-proto3",
				"Prisma.prisma",
				"bradlc.vscode-tailwindcss",
				"csstools.postcss",
				"GraphQL.vscode-graphql-syntax",
				"esbenp.prettier-vscode",
				"firsttris.vscode-jest-runner"
			]
		}
	}
}
